[
  {
    "text": "Morning sunlight exposure within 30 minutes of waking helps set your circadian clock and improves sleep quality.",
    "source_title": "Huberman Lab Podcast #2"
  },
  {
    "text": "Cold exposure increases dopamine by up to 250% and the effect can last for hours.",
    "source_title": "Huberman Lab Podcast #20"
  },
  {
    "text": "Zone 2 cardio training improves mitochondrial function and is one of the best predictors of longevity.",
    "source_title": "Huberman Lab Podcast #12"
  },
  {
    "text": "Consistent sleep and wake times are more important than total sleep duration for circadian health.",
    "source_title": "Huberman Lab Podcast #31"
  },
  {
    "text": "Breathing techniques can rapidly shift your nervous system from stress to calm in under 5 minutes.",
    "source_title": "Huberman Lab Podcast #28"
  }
]
